enindex_tools/__init__.py
enindex_tools/api.py
enindex_tools/api_client.py
enindex_tools/config.py
enindex_tools/token_manager.py
enindex_tools-0.1.3.dist-info/LICENSE
enindex_tools-0.1.3.dist-info/METADATA
enindex_tools-0.1.3.dist-info/WHEEL
enindex_tools-0.1.3.dist-info/RECORD
