Metadata-Version: 2.1
Name: enindex-tools
Version: 0.1.3
Summary: Tools for using the enindex api
License: GNU GPL v3
Author: Paul Rowe-Jones
Requires-Python: >=3.10,<4.0
Classifier: License :: Other/Proprietary License
Classifier: Programming Language :: Python :: 3
Classifier: Programming Language :: Python :: 3.10
Classifier: Programming Language :: Python :: 3.11
Classifier: Programming Language :: Python :: 3.12
Requires-Dist: pandas (>=2.2.2,<3.0.0)
Requires-Dist: python-dotenv (>=1.0.1,<2.0.0)
Requires-Dist: ratelimit (>=2.2.1,<3.0.0)
Requires-Dist: requests (>=2.32.3,<3.0.0)
